[
  {
    "title":"Mr.",
    "first_name":"Michael",
    "last_name":"Hughes",
    "table_number":"OlinTable2",
    "last_name_first_char":"H",
    "Are they able to attend?":"Yes",
    "Entree":"Vegetarian"
  },
  {
    "title":"Miss",
    "first_name":"Heena",
    "last_name":"Mutha",
    "table_number":"OlinTable2",
    "last_name_first_char":"M",
    "Are they able to attend?":"Yes",
    "Entree":"Vegetarian"
  },
  {
    "title":"Ms.",
    "first_name":"Emily",
    "last_name":"Hart",
    "table_number":"OlinNortheastern",
    "last_name_first_char":"H",
    "Are they able to attend?":"Yes",
    "Entree":"Meat"
  },
  {
    "title":"Mr.",
    "first_name":"Wesley",
    "last_name":"Chen",
    "table_number":"MathCamp",
    "last_name_first_char":"C",
    "Are they able to attend?":"Yes",
    "Entree":"Meat"
  },
  {
    "title":"Mr.",
    "first_name":"Andrew",
    "last_name":"Hsiau",
    "table_number":"MathCamp",
    "last_name_first_char":"H",
    "Are they able to attend?":"Yes",
    "Entree":"Meat"
  },
  {
    "title":"Ms.",
    "first_name":"Jasmin",
    "last_name":"Salinas",
    "table_number":"DanielTable",
    "last_name_first_char":"S",
    "Are they able to attend?":"Yes",
    "Entree":"Meat"
  },
  {
    "title":"Mr.",
    "first_name":"Matt",
    "last_name":"Ritter",
    "table_number":"OlinNortheastern",
    "last_name_first_char":"R",
    "Are they able to attend?":"Yes",
    "Entree":"Gluten Free"
  },
  {
    "title":"Miss",
    "first_name":"Meredith",
    "last_name":"Hall",
    "table_number":"OlinNortheastern",
    "last_name_first_char":"H",
    "Are they able to attend?":"Yes",
    "Entree":"Meat"
  },
  {
    "title":"Miss",
    "first_name":"Karla",
    "last_name":"Vazquez",
    "table_number":"MathCamp",
    "last_name_first_char":"V",
    "Are they able to attend?":"Yes",
    "Entree":"Meat"
  },
  {
    "title":"Miss",
    "first_name":"Nicole",
    "last_name":"Norwood",
    "table_number":"MathCamp",
    "last_name_first_char":"N",
    "Are they able to attend?":"Yes",
    "Entree":"Meat"
  },
  {
    "title":"Mr.",
    "first_name":"Oscar",
    "last_name":"Diaz",
    "table_number":"GilTable",
    "last_name_first_char":"D",
    "Are they able to attend?":"Yes",
    "Entree":"Meat"
  },
  {
    "title":"Mrs.",
    "first_name":"Martha",
    "last_name":"Gil ",
    "table_number":"GilTable",
    "last_name_first_char":"G",
    "Are they able to attend?":"Yes",
    "Entree":"Meat"
  },
  {
    "title":"Mr.",
    "first_name":"Carlos",
    "last_name":"Vazquez",
    "table_number":"ParentsTable",
    "last_name_first_char":"V",
    "Are they able to attend?":"Yes",
    "Entree":"Meat"
  },
  {
    "title":"Mrs.",
    "first_name":"Silvia",
    "last_name":"Vazquez",
    "table_number":"ParentsTable",
    "last_name_first_char":"V",
    "Are they able to attend?":"Yes",
    "Entree":"Meat"
  },
  {
    "title":"Mr.",
    "first_name":"Jos&eacute;",
    "last_name":"Gil",
    "table_number":"GilTable",
    "last_name_first_char":"G",
    "Are they able to attend?":"Yes",
    "Entree":"Meat"
  },
  {
    "title":"Ms.",
    "first_name":"Ana Luisa",
    "last_name":"Gil",
    "table_number":"GilTable",
    "last_name_first_char":"G",
    "Are they able to attend?":"Yes",
    "Entree":"Meat"
  },
  {
    "title":"Mr.",
    "first_name":"Josue",
    "last_name":"Gil",
    "table_number":"GilTable",
    "last_name_first_char":"G",
    "Are they able to attend?":"Yes",
    "Entree":"Meat"
  },
  {
    "title":"Mr.",
    "first_name":"Carlos",
    "last_name":"Gil",
    "table_number":"GilTable",
    "last_name_first_char":"G",
    "Are they able to attend?":"Yes",
    "Entree":"Meat"
  },
  {
    "title":"Ms.",
    "first_name":"Nohemi",
    "last_name":"Trevi&ntilde;o",
    "table_number":"GilTable",
    "last_name_first_char":"T",
    "Are they able to attend?":"Yes",
    "Entree":"Meat"
  },
  {
    "title":"Miss",
    "first_name":"Maja",
    "last_name":"Wichrowska",
    "table_number":"MathCamp",
    "last_name_first_char":"W",
    "Are they able to attend?":"Yes",
    "Entree":"Meat"
  },
  {
    "title":"Mr.",
    "first_name":"Luis",
    "last_name":"Salinas",
    "table_number":"PeachTable",
    "last_name_first_char":"S",
    "Are they able to attend?":"Yes",
    "Entree":"Meat"
  },
  {
    "title":"Mrs.",
    "first_name":"Jessica",
    "last_name":"Salinas",
    "table_number":"PeachTable",
    "last_name_first_char":"S",
    "Are they able to attend?":"Yes",
    "Entree":"Meat"
  },
  {
    "title":"Mr.",
    "first_name":"Gerry",
    "last_name":"Salinas",
    "table_number":"DanielTable",
    "last_name_first_char":"S",
    "Are they able to attend?":"Yes",
    "Entree":"Meat"
  },
  {
    "title":"Mr.",
    "first_name":"Alex",
    "last_name":"Salinas",
    "table_number":"BenCousinsTable",
    "last_name_first_char":"S",
    "Are they able to attend?":"Yes",
    "Entree":"Meat"
  },
  {
    "title":"Miss",
    "first_name":"Lillie",
    "last_name":"Greenwood",
    "table_number":"BenCousinsTable",
    "last_name_first_char":"G",
    "Are they able to attend?":"Yes",
    "Entree":"Meat"
  },
  {
    "title":"Mr.",
    "first_name":"Ovidio",
    "last_name":"Garza",
    "table_number":"GilVazquez",
    "last_name_first_char":"G",
    "Are they able to attend?":"Yes",
    "Entree":"Meat"
  },
  {
    "title":"Mrs.",
    "first_name":"Irma",
    "last_name":"Gil",
    "table_number":"GilVazquez",
    "last_name_first_char":"G",
    "Are they able to attend?":"Yes",
    "Entree":"Meat"
  },
  {
    "title":"Miss",
    "first_name":"Irma",
    "last_name":"Garza",
    "table_number":"GilVazquez",
    "last_name_first_char":"G",
    "Are they able to attend?":"Yes",
    "Entree":"Meat"
  },
  {
    "title":"Mr.",
    "first_name":"Ovidio Cesar",
    "last_name":"Garza",
    "table_number":"GilVazquez",
    "last_name_first_char":"G",
    "Are they able to attend?":"Yes",
    "Entree":"Meat"
  },
  {
    "title":"Mrs.",
    "first_name":"Karina",
    "last_name":"Gonzalez",
    "table_number":"GilVazquez",
    "last_name_first_char":"G",
    "Are they able to attend?":"Yes",
    "Entree":"Meat"
  },
  {
    "title":"Mr.",
    "first_name":"Alfonso",
    "last_name":"Gonzalez",
    "table_number":"GilVazquez",
    "last_name_first_char":"G",
    "Are they able to attend?":"Yes",
    "Entree":"Meat"
  },
  {
    "title":"Ms.",
    "first_name":"Irma",
    "last_name":"Quintanilla",
    "table_number":"ParentsTable",
    "last_name_first_char":"Q",
    "Are they able to attend?":"Yes",
    "Entree":"Meat"
  },
  {
    "title":"Mr.",
    "first_name":"George",
    "last_name":"Pyle",
    "table_number":"ThePyles",
    "last_name_first_char":"P",
    "Are they able to attend?":"Yes",
    "Entree":"Vegetarian"
  },
  {
    "title":"Mrs.",
    "first_name":"Libby ",
    "last_name":"Pyle",
    "table_number":"ThePyles",
    "last_name_first_char":"P",
    "Are they able to attend?":"Yes",
    "Entree":"Meat"
  },
  {
    "title":"Mr.",
    "first_name":"Brendan",
    "last_name":"Smith",
    "table_number":"ThePyles",
    "last_name_first_char":"S",
    "Are they able to attend?":"Yes",
    "Entree":"Meat"
  },
  {
    "title":"Mrs.",
    "first_name":"Natalie",
    "last_name":"Smith",
    "table_number":"ThePyles",
    "last_name_first_char":"S",
    "Are they able to attend?":"Yes",
    "Entree":"Vegetarian"
  },
  {
    "title":"Miss",
    "first_name":"Carolyn",
    "last_name":"Smith",
    "table_number":"ThePyles",
    "last_name_first_char":"S",
    "Are they able to attend?":"Yes",
    "Entree":"Meat"
  },
  {
    "title":"Mr.",
    "first_name":"James",
    "last_name":"Pyle",
    "table_number":"ThePyles",
    "last_name_first_char":"P",
    "Are they able to attend?":"Yes",
    "Entree":"Meat"
  },
  {
    "title":"Mrs.",
    "first_name":"Veronica",
    "last_name":"Pyle",
    "table_number":"ThePyles",
    "last_name_first_char":"P",
    "Are they able to attend?":"Yes",
    "Entree":"Meat"
  },
  {
    "title":"Ms.",
    "first_name":"Patricia",
    "last_name":"Pyle",
    "table_number":"ThePyles",
    "last_name_first_char":"P",
    "Are they able to attend?":"Yes",
    "Entree":"Meat"
  },
  {
    "title":"Ms.",
    "first_name":"Clarissa",
    "last_name":"Pyle",
    "table_number":"ThePyles",
    "last_name_first_char":"P",
    "Are they able to attend?":"Yes",
    "Entree":"Meat"
  },
  {
    "title":"Ms.",
    "first_name":"Kellie",
    "last_name":"Rowlett",
    "table_number":"KarenFriends1",
    "last_name_first_char":"R",
    "Are they able to attend?":"Yes",
    "Entree":"Meat"
  },
  {
    "title":"Mr.",
    "first_name":"Travis",
    "last_name":"Hutchinson",
    "table_number":"KarenFriends1",
    "last_name_first_char":"H",
    "Are they able to attend?":"Yes",
    "Entree":"Meat"
  },
  {
    "title":"Ms.",
    "first_name":"Stephanie",
    "last_name":"Chan",
    "table_number":"MathCamp",
    "last_name_first_char":"C",
    "Are they able to attend?":"Yes",
    "Entree":"Meat"
  },
  {
    "title":"Mr.",
    "first_name":"John",
    "last_name":"Morgan",
    "table_number":"OlinNortheastern",
    "last_name_first_char":"M",
    "Are they able to attend?":"Yes",
    "Entree":"Meat"
  },
  {
    "title":"Ms.",
    "first_name":"Michelle",
    "last_name":"Pruett",
    "table_number":"MathCamp",
    "last_name_first_char":"P",
    "Are they able to attend?":"Yes",
    "Entree":"Vegetarian"
  },
  {
    "title":"Mr.",
    "first_name":"David",
    "last_name":"Peveto",
    "table_number":"MathCamp",
    "last_name_first_char":"P",
    "Are they able to attend?":"Yes",
    "Entree":"Meat"
  },
  {
    "title":"Ms.",
    "first_name":"Meredith",
    "last_name":"Grabscheid",
    "table_number":"OlinNortheastern",
    "last_name_first_char":"G",
    "Are they able to attend?":"Yes",
    "Entree":"Meat"
  },
  {
    "title":"Mr.",
    "first_name":"Carl",
    "last_name":"Tappan",
    "table_number":"OlinTable2",
    "last_name_first_char":"T",
    "Are they able to attend?":"Yes",
    "Entree":"Meat"
  },
  {
    "title":"Mrs.",
    "first_name":"Juanita ",
    "last_name":"Prazak ",
    "table_number":"DanielTable",
    "last_name_first_char":"P",
    "Are they able to attend?":"Yes",
    "Entree":"Meat"
  },
  {
    "title":"Mr.",
    "first_name":"Michael ",
    "last_name":"Prazak",
    "table_number":"DanielTable",
    "last_name_first_char":"P",
    "Are they able to attend?":"Yes",
    "Entree":"Meat"
  },
  {
    "title":"Mr.",
    "first_name":"Scott",
    "last_name":"Cartwright",
    "table_number":"OlinNortheastern",
    "last_name_first_char":"C",
    "Are they able to attend?":"Yes",
    "Entree":"Meat"
  },
  {
    "title":"Mr.",
    "first_name":"Vasileios",
    "last_name":"Ioannou",
    "table_number":"OlinNortheastern",
    "last_name_first_char":"I",
    "Are they able to attend?":"Yes",
    "Entree":"Meat"
  },
  {
    "title":"Ms.",
    "first_name":"Libby",
    "last_name":"Hollinger",
    "table_number":"KarenFriends2",
    "last_name_first_char":"H",
    "Are they able to attend?":"Yes",
    "Entree":"Meat"
  },
  {
    "title":"Mr.",
    "first_name":"Mike",
    "last_name":"Gonzales",
    "table_number":"KarenFriends2",
    "last_name_first_char":"G",
    "Are they able to attend?":"Yes",
    "Entree":"Meat"
  },
  {
    "title":"Mr.",
    "first_name":"Humberto ",
    "last_name":"Ibarra",
    "table_number":"GilTable",
    "last_name_first_char":"I",
    "Are they able to attend?":"Yes",
    "Entree":"Meat"
  },
  {
    "title":"Mrs.",
    "first_name":"Yocasta",
    "last_name":"Garza Rosalez",
    "table_number":"GilTable",
    "last_name_first_char":"G",
    "Are they able to attend?":"Yes",
    "Entree":"Meat"
  },
  {
    "title":"Mr.",
    "first_name":"Roberto",
    "last_name":"Jimenez",
    "table_number":"GilVazquez",
    "last_name_first_char":"J",
    "Are they able to attend?":"Yes",
    "Entree":"Meat"
  },
  {
    "title":"Mrs.",
    "first_name":"Stella",
    "last_name":"Garcia",
    "table_number":"GilVazquez",
    "last_name_first_char":"G",
    "Are they able to attend?":"Yes",
    "Entree":"Meat"
  },
  {
    "title":"Miss",
    "first_name":"Alejandra",
    "last_name":"Jimenez",
    "table_number":"GilVazquez",
    "last_name_first_char":"J",
    "Are they able to attend?":"Yes",
    "Entree":"Meat"
  },
  {
    "title":"Miss",
    "first_name":"Cristina",
    "last_name":"Jimenez",
    "table_number":"GilVazquez",
    "last_name_first_char":"J",
    "Are they able to attend?":"Yes",
    "Entree":"Meat"
  },
  {
    "title":"Mrs.",
    "first_name":"Patricia ",
    "last_name":"Hernandez",
    "table_number":"ParentsTable",
    "last_name_first_char":"H",
    "Are they able to attend?":"Yes",
    "Entree":"Meat"
  },
  {
    "title":"Miss",
    "first_name":"George",
    "last_name":"Harris",
    "table_number":"OlinTable2",
    "last_name_first_char":"H",
    "Are they able to attend?":"Yes",
    "Entree":"Meat"
  },
  {
    "title":"Ms.",
    "first_name":"Glennis",
    "last_name":"Rayermann",
    "table_number":"OlinTable2",
    "last_name_first_char":"R",
    "Are they able to attend?":"Yes",
    "Entree":"Meat"
  },
  {
    "title":"Ms.",
    "first_name":"Rebecca",
    "last_name":"Salinas",
    "table_number":"BenCousinsTable",
    "last_name_first_char":"S",
    "Are they able to attend?":"Yes",
    "Entree":"Meat"
  },
  {
    "title":"Mr.",
    "first_name":"Christian ",
    "last_name":"Werline ",
    "table_number":"BenCousinsTable",
    "last_name_first_char":"W",
    "Are they able to attend?":"Yes",
    "Entree":"Meat"
  },
  {
    "title":"Mr.",
    "first_name":"Stefan",
    "last_name":"Wolpert",
    "table_number":"OlinTable2",
    "last_name_first_char":"W",
    "Are they able to attend?":"Yes",
    "Entree":"Meat"
  },
  {
    "title":"Mrs.",
    "first_name":"Sarah",
    "last_name":"Wolpert",
    "table_number":"OlinTable2",
    "last_name_first_char":"W",
    "Are they able to attend?":"Yes",
    "Entree":"Meat"
  },
  {
    "title":"Mr.",
    "first_name":"Andrew",
    "last_name":"Coats",
    "table_number":"OlinTable2",
    "last_name_first_char":"C",
    "Are they able to attend?":"Yes",
    "Entree":"Meat"
  },
  {
    "title":"Ms.",
    "first_name":"Susan",
    "last_name":"Tse",
    "table_number":"OlinTable2",
    "last_name_first_char":"T",
    "Are they able to attend?":"Yes",
    "Entree":"Meat"
  },
  {
    "title":"Mr.",
    "first_name":"Mario",
    "last_name":"Contreras",
    "table_number":"KarenFriends1",
    "last_name_first_char":"C",
    "Are they able to attend?":"Yes",
    "Entree":"Meat"
  },
  {
    "title":"Mr.",
    "first_name":"Ben",
    "last_name":"Steffy",
    "table_number":"KarenFriends1",
    "last_name_first_char":"S",
    "Are they able to attend?":"Yes",
    "Entree":"Meat"
  },
  {
    "title":"Mrs.",
    "first_name":"Erin",
    "last_name":"Schmidt",
    "table_number":"KarenFriends2",
    "last_name_first_char":"S",
    "Are they able to attend?":"Yes",
    "Entree":"Meat"
  },
  {
    "title":"Mr.",
    "first_name":"Hunter",
    "last_name":"Schmidt",
    "table_number":"KarenFriends2",
    "last_name_first_char":"S",
    "Are they able to attend?":"Yes",
    "Entree":"Meat"
  },
  {
    "title":"Ms.",
    "first_name":"Debbie",
    "last_name":"Kalashian",
    "table_number":"OlinNortheastern",
    "last_name_first_char":"K",
    "Are they able to attend?":"Yes",
    "Entree":"Meat"
  },
  {
    "title":"Mr.",
    "first_name":"Austin",
    "last_name":"Charette",
    "table_number":"OlinNortheastern",
    "last_name_first_char":"C",
    "Are they able to attend?":"Yes",
    "Entree":"Meat"
  },
  {
    "title":"Mr.",
    "first_name":"Felipe",
    "last_name":"Salinas",
    "table_number":"ParentsTable",
    "last_name_first_char":"S",
    "Are they able to attend?":"Yes",
    "Entree":"Meat"
  },
  {
    "title":"Mrs.",
    "first_name":"Cathy",
    "last_name":"Salinas",
    "table_number":"ParentsTable",
    "last_name_first_char":"S",
    "Are they able to attend?":"Yes",
    "Entree":"Meat"
  },
  {
    "title":"Ms.",
    "first_name":"Hannah",
    "last_name":"Salinas",
    "table_number":"BenCousinsTable",
    "last_name_first_char":"S",
    "Are they able to attend?":"Yes",
    "Entree":"Vegetarian"
  },
  {
    "title":"Mr.",
    "first_name":"Daniel",
    "last_name":"Salinas ",
    "table_number":"DanielTable",
    "last_name_first_char":"S",
    "Are they able to attend?":"Yes",
    "Entree":"Meat"
  },
  {
    "title":"Dr.",
    "first_name":"Tammy",
    "last_name":"Zhou",
    "table_number":"DanielTable",
    "last_name_first_char":"Z",
    "Are they able to attend?":"Yes",
    "Entree":"Meat"
  },
  {
    "title":"Mrs.",
    "first_name":"Marta",
    "last_name":"Salinas-Hovar",
    "table_number":"RinaTable",
    "last_name_first_char":"S",
    "Are they able to attend?":"Yes",
    "Entree":"Meat"
  },
  {
    "title":"Mr.",
    "first_name":"Michael ",
    "last_name":"Hovar",
    "table_number":"RinaTable",
    "last_name_first_char":"H",
    "Are they able to attend?":"Yes",
    "Entree":"Meat"
  },
  {
    "title":"Ms.",
    "first_name":"Mercedes",
    "last_name":"Espinosa",
    "table_number":"PeachTable",
    "last_name_first_char":"E",
    "Are they able to attend?":"Yes",
    "Entree":"Meat"
  },
  {
    "title":"Mr.",
    "first_name":"Pete",
    "last_name":"Espinosa",
    "table_number":"PeachTable",
    "last_name_first_char":"E",
    "Are they able to attend?":"Yes",
    "Entree":"Meat"
  },
  {
    "title":"Mr.",
    "first_name":"Lucas",
    "last_name":"Espinosa",
    "table_number":"PeachTable",
    "last_name_first_char":"E",
    "Are they able to attend?":"Yes",
    "Entree":"Meat"
  },
  {
    "title":"Ms.",
    "first_name":"Sarah ",
    "last_name":"Espinosa",
    "table_number":"PeachTable",
    "last_name_first_char":"E",
    "Are they able to attend?":"Yes",
    "Entree":"Meat"
  },
  {
    "title":"Mr.",
    "first_name":"David",
    "last_name":"Hovar",
    "table_number":"BenCousinsTable",
    "last_name_first_char":"H",
    "Are they able to attend?":"Yes",
    "Entree":"Vegetarian"
  },
  {
    "title":"Mr.",
    "first_name":"Hayden",
    "last_name":"Dooley",
    "table_number":"KarenFriends1",
    "last_name_first_char":"D",
    "Are they able to attend?":"Yes",
    "Entree":"Meat"
  },
  {
    "title":"Miss",
    "first_name":" Maribel",
    "last_name":"Ryburn",
    "table_number":"KarenFriends1",
    "last_name_first_char":"R",
    "Are they able to attend?":"Yes",
    "Entree":"Vegetarian"
  },
  {
    "title":"Mr.",
    "first_name":"Wesley",
    "last_name":"Barlow",
    "table_number":"RinaTable",
    "last_name_first_char":"B",
    "Are they able to attend?":"Yes",
    "Entree":"Meat"
  },
  {
    "title":"Mrs.",
    "first_name":"Karina",
    "last_name":"Barlow",
    "table_number":"RinaTable",
    "last_name_first_char":"B",
    "Are they able to attend?":"Yes",
    "Entree":"Meat"
  },
  {
    "title":"Mr.",
    "first_name":"Jack",
    "last_name":"Barlow",
    "table_number":"RinaTable",
    "last_name_first_char":"B",
    "Are they able to attend?":"Yes",
    "Entree":"Meat"
  },
  {
    "title":"Mr.",
    "first_name":"Nikolaus",
    "last_name":"Barlow",
    "table_number":"RinaTable",
    "last_name_first_char":"B",
    "Are they able to attend?":"Yes",
    "Entree":"Meat"
  },
  {
    "title":"Mr.",
    "first_name":"Danny",
    "last_name":"Salinas",
    "table_number":"DanielTable",
    "last_name_first_char":"S",
    "Are they able to attend?":"Yes",
    "Entree":"Meat"
  },
  {
    "title":"Miss",
    "first_name":"Eliana",
    "last_name":"Salinas",
    "table_number":"BenCousinsTable",
    "last_name_first_char":"S",
    "Are they able to attend?":"Yes",
    "Entree":"Meat"
  },
  {
    "title":"Mrs.",
    "first_name":"Deborah ",
    "last_name":"Salinas",
    "table_number":"PeachTable",
    "last_name_first_char":"S",
    "Are they able to attend?":"Yes",
    "Entree":"Meat"
  },
  {
    "title":"Mr.",
    "first_name":"Gideon",
    "last_name":"Lee",
    "table_number":"KarenFriends1",
    "last_name_first_char":"L",
    "Are they able to attend?":"Yes",
    "Entree":"Meat"
  },
  {
    "title":"Mr.",
    "first_name":"Ben",
    "last_name":"Salinas",
    "table_number":"BenAndKarenTable",
    "last_name_first_char":"S",
    "Are they able to attend?":"Yes",
    "Entree":"Meat"
  },
  {
    "title":"Ms.",
    "first_name":"Karen",
    "last_name":"Vazquez",
    "table_number":"BenAndKarenTable",
    "last_name_first_char":"V",
    "Are they able to attend?":"Yes",
    "Entree":"Meat"
  },
  {
    "title":"Ms.",
    "first_name":"Nicole",
    "last_name":"Bennett",
    "table_number":"KarenFriends1",
    "last_name_first_char":"B",
    "Are they able to attend?":"Yes",
    "Entree":"Gluten Free"
  },
  {
    "title":"Mr.",
    "first_name":"Seth ",
    "last_name":"Bruton ",
    "table_number":"KarenFriends1",
    "last_name_first_char":"B",
    "Are they able to attend?":"Yes",
    "Entree":"Meat"
  },
  {
    "title":"Mr.",
    "first_name":"Marty ",
    "last_name":"Morris",
    "table_number":"SouthTexas",
    "last_name_first_char":"M",
    "Are they able to attend?":"Yes",
    "Entree":"Meat"
  },
  {
    "title":"Mrs.",
    "first_name":"Rise",
    "last_name":"Morris",
    "table_number":"SouthTexas",
    "last_name_first_char":"M",
    "Are they able to attend?":"Yes",
    "Entree":"Meat"
  },
  {
    "title":"Mr.",
    "first_name":"Michael",
    "last_name":"Morris",
    "table_number":"SouthTexas",
    "last_name_first_char":"M",
    "Are they able to attend?":"Yes",
    "Entree":"Meat"
  },
  {
    "title":"Mr.",
    "first_name":"Chester",
    "last_name":"Macklin",
    "table_number":"OlinTable2",
    "last_name_first_char":"M",
    "Are they able to attend?":"Yes",
    "Entree":"Meat"
  },
  {
    "title":"Mrs.",
    "first_name":"Debbie",
    "last_name":"Arfele",
    "table_number":"SouthTexas",
    "last_name_first_char":"A",
    "Are they able to attend?":"Yes",
    "Entree":"Meat"
  },
  {
    "title":"Mr.",
    "first_name":"Benny",
    "last_name":"Arfele",
    "table_number":"SouthTexas",
    "last_name_first_char":"A",
    "Are they able to attend?":"Yes",
    "Entree":"Meat"
  },
  {
    "title":"Ms.",
    "first_name":"Judy",
    "last_name":"MacArthur",
    "table_number":"ParentsTable",
    "last_name_first_char":"M",
    "Are they able to attend?":"Yes",
    "Entree":"Meat"
  },
  {
    "title":"Mr.",
    "first_name":"Thom",
    "last_name":"Pravel",
    "table_number":"SouthTexas",
    "last_name_first_char":"P",
    "Are they able to attend?":"Yes",
    "Entree":"Meat"
  },
  {
    "title":"Mrs.",
    "first_name":"Victoria",
    "last_name":"PLACEHOLDER Muniz",
    "table_number":"100000000",
    "last_name_first_char":"P",
    "Are they able to attend?":"Yes",
    "Entree":"Meat"
  },
  {
    "title":"Mr.",
    "first_name":"Beto",
    "last_name":"PLACEHOLDER Muniz",
    "table_number":"100000000",
    "last_name_first_char":"P",
    "Are they able to attend?":"Yes",
    "Entree":"Meat"
  },
  {
    "title":"Ms.",
    "first_name":"Sophia",
    "last_name":"PLACEHOLDER Muniz",
    "table_number":"100000000",
    "last_name_first_char":"P",
    "Are they able to attend?":"Yes",
    "Entree":"Meat"
  },
  {
    "title":"Mr.",
    "first_name":"Frank",
    "last_name":"PLACEHOLDER",
    "table_number":"100000000",
    "last_name_first_char":"P",
    "Are they able to attend?":"Yes",
    "Entree":"Meat"
  },
  {
    "title":"Mrs.",
    "first_name":"Krystel",
    "last_name":"PLACEHOLDER",
    "table_number":"100000000",
    "last_name_first_char":"P",
    "Are they able to attend?":"Yes",
    "Entree":"Meat"
  },
  {
    "title":"Ms.",
    "first_name":"Frank Kid",
    "last_name":"PLACEHOLDER",
    "table_number":"100000000",
    "last_name_first_char":"P",
    "Are they able to attend?":"Yes",
    "Entree":"Meat"
  },
  {
    "title":"Ms.",
    "first_name":"Frank Kid",
    "last_name":"PLACEHOLDER",
    "table_number":"100000000",
    "last_name_first_char":"P",
    "Are they able to attend?":"Yes",
    "Entree":"Meat"
  },
  {
    "title":"Mr.",
    "first_name":"Manuel",
    "last_name":"PLACEHOLDER Sanchez",
    "table_number":"100000000",
    "last_name_first_char":"P",
    "Are they able to attend?":"Yes",
    "Entree":"Meat"
  },
  {
    "title":"Mrs.",
    "first_name":"Martha",
    "last_name":"PLACEHOLDER Sanchez",
    "table_number":"100000000",
    "last_name_first_char":"P",
    "Are they able to attend?":"Yes",
    "Entree":"Meat"
  },
  {
    "title":"Mr.",
    "first_name":"John",
    "last_name":"Pravel",
    "table_number":"SouthTexas",
    "last_name_first_char":"P",
    "Are they able to attend?":"Yes",
    "Entree":"Meat"
  },
  {
    "title":"Mr.",
    "first_name":"Micah",
    "last_name":"Pravel",
    "table_number":"SouthTexas",
    "last_name_first_char":"P",
    "Are they able to attend?":"Yes",
    "Entree":"Meat"
  },
  {
    "title":"Mr.",
    "first_name":"Joshua",
    "last_name":"Pravel",
    "table_number":"SouthTexas",
    "last_name_first_char":"P",
    "Are they able to attend?":"Yes",
    "Entree":"Meat"
  },
  {
    "title":"Ms.",
    "first_name":"Ann Williams",
    "last_name":"Cass",
    "table_number":"SouthTexas",
    "last_name_first_char":"C",
    "Are they able to attend?":"Yes",
    "Entree":"Meat"
  },
  {
    "title":"Ms.",
    "first_name":"Valerie",
    "last_name":"Creveling",
    "table_number":"MathCamp",
    "last_name_first_char":"C",
    "Are they able to attend?":"Yes",
    "Entree":"Meat"
  },
  {
    "title":"Mr.",
    "first_name":"Jon",
    "last_name":"Agee",
    "table_number":"MathCamp",
    "last_name_first_char":"A",
    "Are they able to attend?":"Yes",
    "Entree":"Meat"
  },
  {
    "title":"Mr.",
    "first_name":"Aamir",
    "last_name":"Ali",
    "table_number":"BenCousinsTable",
    "last_name_first_char":"A",
    "Are they able to attend?":"Yes",
    "Entree":"Meat"
  },
  {
    "title":"Ms.",
    "first_name":"Elyse",
    "last_name":"Pravel",
    "table_number":"BenCousinsTable",
    "last_name_first_char":"P",
    "Are they able to attend?":"Yes",
    "Entree":"Meat"
  },
  {
    "title":"Ms.",
    "first_name":"Gina",
    "last_name":"Santos Olague",
    "table_number":"RinaTable",
    "last_name_first_char":"S",
    "Are they able to attend?":"Yes",
    "Entree":"Meat"
  },
  {
    "title":"Miss",
    "first_name":"Vania",
    "last_name":"Santos",
    "table_number":"RinaTable",
    "last_name_first_char":"S",
    "Are they able to attend?":"Yes",
    "Entree":"Meat"
  },
  {
    "title":"Mr.",
    "first_name":"Jorge",
    "last_name":"Delgado",
    "table_number":"RinaTable",
    "last_name_first_char":"D",
    "Are they able to attend?":"Yes",
    "Entree":"Meat"
  },
  {
    "title":"Mr.",
    "first_name":"Steven",
    "last_name":"Ross",
    "table_number":"ParentsTable",
    "last_name_first_char":"R",
    "Are they able to attend?":"Yes",
    "Entree":"Meat"
  }
]